odadoc/__init__.py
odadoc/index.py
oda_doc-0.1.0.dist-info/COPYING
oda_doc-0.1.0.dist-info/METADATA
oda_doc-0.1.0.dist-info/WHEEL
oda_doc-0.1.0.dist-info/entry_points.txt
oda_doc-0.1.0.dist-info/top_level.txt
oda_doc-0.1.0.dist-info/RECORD
