Metadata-Version: 2.1
Name: oda-doc
Version: 0.1.0
Summary: oda-doc
Home-page: https://odahub.io/
Author: V.S.
Author-email: vladimir.savchenko@gmail.com
License: GPL-2+
Platform: UNKNOWN
Classifier: Development Status :: 4 - Beta
Classifier: Environment :: Console
Classifier: Intended Audience :: Science/Research
Classifier: License :: OSI Approved :: GNU General Public License v2 or later (GPLv2+)
Classifier: Operating System :: POSIX
Classifier: Programming Language :: Python :: 2.7
Classifier: Programming Language :: Python :: 3.4
Classifier: Programming Language :: Python :: 3.5
Classifier: Programming Language :: Python :: 3.6
Classifier: Programming Language :: Python :: 3.7
Classifier: Topic :: Internet
Classifier: Topic :: Scientific/Engineering :: Astronomy
Requires-Dist: lxml
Requires-Dist: six
Requires-Dist: coloredlogs
Requires-Dist: path.py
Requires-Dist: minio
Requires-Dist: keyring
Requires-Dist: keyrings.cryptfile
Requires-Dist: click
Requires-Dist: pyyaml
Requires-Dist: numpy
Provides-Extra: cwl
Requires-Dist: cwltool ; extra == 'cwl'
Provides-Extra: notebook
Requires-Dist: nb2workflow ; extra == 'notebook'
Requires-Dist: papermill ; extra == 'notebook'
Provides-Extra: rdf
Requires-Dist: rdflib ; extra == 'rdf'
Requires-Dist: rdflib-jsonld ; extra == 'rdf'
